plotynium/__init__.py
plotynium/context.py
plotynium/dimensions.py
plotynium/domain.py
plotynium/interpolations.py
plotynium/options.py
plotynium/plot.py
plotynium/properties.py
plotynium/scaler.py
plotynium/schemes.py
plotynium/symbols.py
plotynium/types.py
plotynium/legends/__init__.py
plotynium/legends/continuous_color.py
plotynium/legends/default_scheme.py
plotynium/legends/discrete_color.py
plotynium/legends/string_widths.py
plotynium/legends/symbol.py
plotynium/marks/__init__.py
plotynium/marks/area.py
plotynium/marks/axis.py
plotynium/marks/bar.py
plotynium/marks/dot.py
plotynium/marks/grid.py
plotynium/marks/line.py
plotynium/marks/mark.py
plotynium/marks/rule.py
plotynium/marks/style.py
plotynium/marks/text.py
plotynium/transformers/__init__.py
plotynium/transformers/color.py
plotynium/transformers/constant.py
plotynium/transformers/default.py
plotynium/transformers/getter.py
plotynium/transformers/identity.py
plotynium/transformers/picker.py
plotynium/transformers/symbol.py
plotynium/transformers/transformer.py
plotynium-0.1.0.dist-info/licenses/LICENSE
plotynium-0.1.0.dist-info/METADATA
plotynium-0.1.0.dist-info/WHEEL
plotynium-0.1.0.dist-info/top_level.txt
plotynium-0.1.0.dist-info/RECORD
