Metadata-Version: 2.4
Name: plotynium
Version: 0.1.0
Summary: plotynium is a Data Visualization framework for Python, inspired by Observable Plot
Author-email: Benjamin BOURBON <ben.bourbon06@gmail.com>
License-Expression: MIT
Project-URL: Homepage, https://github.com/bourbonut/plotynium
Project-URL: Repository, https://github.com/bourbonut/plotynium
Project-URL: Documentation, https://bourbonut.github.io/plotynium/
Classifier: Programming Language :: Python
Classifier: Programming Language :: Python :: 3.10
Classifier: Programming Language :: Python :: 3.11
Classifier: Programming Language :: Python :: 3.12
Classifier: Topic :: Scientific/Engineering :: Visualization
Requires-Python: >=3.10
License-File: LICENSE
Requires-Dist: detroit>=2.3.0
Dynamic: license-file
